{
    "version": "0.43.0",
    "description": "A fast, secure, and intelligent code snippet manager",
    "homepage": "https://github.com/1jehuang/jcode",
    "license": "MIT",
    "architecture": {
        "64bit": {
            "url": "https://github.com/1jehuang/jcode/releases/download/v0.43.0/jcode-windows-x86_64.exe#/jcode.exe",
            "hash": "f221fe370790927e7e2fdcbc20f4070f6097e1eb889f9a21d7c92b10a1c092c4"
        }
    },
    "bin": "jcode.exe",
    "checkver": {
        "github": "https://github.com/1jehuang/jcode"
    },
    "autoupdate": {
        "architecture": {
            "64bit": {
                "url": "https://github.com/1jehuang/jcode/releases/download/v$version/jcode-windows-x86_64.exe#/jcode.exe",
                "hash": {
                    "url": "https://api.github.com/repos/1jehuang/jcode/releases/tags/v$version",
                    "jp": "$.assets[?(@.name=='jcode-windows-x86_64.exe')].digest"
                }
            }
        }
    }
}
